{
  "store": {
    "name": "Sohayb grove",
    "logo": "images/logo.png",
    "tagline": "Handmade candles for every occasion",
    "currency": "LE",
    "whatsApp": "https://wa.me/201080110619",
    "instagram": "https://www.instagram.com/sohaybgrove?igsh=ZmMzMWhkZ3Y4MzFp",
    "facebook": "https://www.facebook.com/share/1BW7WMce9G/",
    "tiktok": "https://www.tiktok.com/@sohaybgrove?_r=1&_t=ZS-97rrjILMtfe"
  },
  "theme" : {
    "primaryColor": "#fff",
    "accentColor": "#000",
    "bgAccentColor": "#000",
    "darkAccentColor": "#000",
    "fontHeading": "Droid Serif",
    "fontBody": "Droid Serif",
    "fontAccent": "Playball"
  },
  "anouncement": {
    "message": "Free shipping on orders over 500 EGP!",
    "link": "/products",
    "linkText": "Shop Now"
  },
  "hero": {
    "title-first": "True taste",
    "title-second": "Begins here, Authintic",
    "subtitle": "Harvest of the year for better health.",
    "description": "Discover our handmade candles, crafted with love and care. Perfect for any occasion.",
    "image": "images/hero.jpeg",
    "ctaText": "Shop Now",
    "ctaLink": "/products",
    "secondaryCtaText": "Custom Order",
    "secondaryCtaLink": "whatsapp://send?phone=+201012425386&text=Hello%20Angles%20for%20Candles%2C%20I%20would%20like%20to%20place%20a%20custom%20order."
  },
  "products": [
    {
      "id": 1,
      "name": "Extra virgin Olive Oil 250 ml",
      "description": "Hand-picked from our family grove in North Sinai. Cold pressed, made from Picual olives, and 100% natural with no additives or chemicals.",
      "price": 240,
      "image": "images/product_250.png"
    },  
    {
      "id": 2,
      "name": "Extra virgin Olive Oil 500 ml",
      "description": "Hand-picked from our family grove in North Sinai. Cold pressed, made from Picual olives, and 100% natural with no additives or chemicals.",
      "price": 420,
      "image": "images/product_500.png"
    }
  ],
  "payment": {
    "methods": [{ "enabled": true, "name": "Wallet", "value": "wallet", "reciever": "01289089376"}, { "enabled": true, "name": "InstaPay", "value": "instapay", "reciever": "01225134007"}, { "enabled": false, "name": "Fawry", "reciever": "xxxxxx", "value": "fawry"}, { "name": "Cash on Delivery", "enabled": true , "value": "cod", "reciever": ""}],
    "currency": "LE"
  },
  "pages": [
    {
      "name": "Home",
      "link": "/"
    },
    {
      "name": "Products",
      "link": "#catalog"
    },
    {
      "name": "About Us",
      "link": "#about"
    },
    {
      "name": "Contact",
      "link": "#contact"
    }
  ],
  "about": {
    "title": "Our Story",
    "content": "Sohayb Grove is a family business that started with the planting of the first olive tree by Sohayb’s father, the project wasn’t just simple agricultural project, it was the start of a true value that combines the family’s passion with the quality of the land from North Sinai. We offer premium olive oil for a unique experience worthy of you.",
    "image": "images/about.png",
    "ctaText": "Shop Our Collection",
    "ctaLink": "/products"
  },
  "reviews": [
    {
      "name": "Ahmed Eid",
      "rating": 5,
      "comment": "El zeit zatoun helw awi msa"
    },
    {
      "name": "Eng.abdelrahman",
      "rating": 5,
      "comment": "جميل جدا ... ريحته حلوة و طعمه جميل تسلم ايدكم"
    },
    {
      "name": "Abdullah",
      "rating": 5,
      "comment": "مساء الخير الزيت كجودة كان جميل وطعمه راق ليا جدا والباكديج للمنتج وصلي متغلف كويس واحييكم علي اللي غلف المنتج التغليف الممتاز دا عشان حصلي اكتر من مره مشكلة بسبب المناديب اللي بتوصلي الحاجه مكسوره او مكببوبه للاسف... فشكرا ليكم"
    },
    {
      "name": "Fatma saad",
      "rating": 5,
      "comment": "كل حاجة حلوة جدا من افضل انواع الزيت اللي جربتها في حياتي وانا بشرب معلقة منه فا مش على الاكل بس وطعمه تحفة  والتغليف كمان"
    }
    
  ]
}